FragenAntwortLLMCPU/__init__.py
FragenAntwortLLMCPU/document_processor.py
tests/__init__.py
tests/test_document_processor.py
FragenAntwortLLMCPU-0.1.17.dist-info/LICENSE
FragenAntwortLLMCPU-0.1.17.dist-info/METADATA
FragenAntwortLLMCPU-0.1.17.dist-info/WHEEL
FragenAntwortLLMCPU-0.1.17.dist-info/dependency_links.txt
FragenAntwortLLMCPU-0.1.17.dist-info/entry_points.txt
FragenAntwortLLMCPU-0.1.17.dist-info/top_level.txt
FragenAntwortLLMCPU-0.1.17.dist-info/RECORD
