Metadata-Version: 2.1
Name: FragenAntwortLLMCPU
Version: 0.1.17
Summary: A package for processing documents and generating questions and answers using LLMs on CPU.
Author: Mehrdad Almasi, Demival VASQUES FILHO, and Lars Wieneke
Author-email: Mehrdad.al.2023@gmail.com, demival.vasques@uni.lu, lars.wieneke@gmail.com
Classifier: Programming Language :: Python :: 3
Classifier: License :: OSI Approved :: MIT License
Classifier: Operating System :: OS Independent
Requires-Python: >=3.6
License-File: LICENSE
Requires-Dist: PyMuPDF
Requires-Dist: tokenizers
Requires-Dist: semantic-text-splitter
Requires-Dist: langchain
Requires-Dist: langchain-community
Requires-Dist: torch
Requires-Dist: torchvision
Requires-Dist: torchaudio
Requires-Dist: ctransformers
